CHANGELOG.txt
LICENSE.txt
MANIFEST.in
README.txt
setup.cfg
setup.py
distro/lucid/debian/control.template
doc/index.txt
doc/source/index.rst
doc/source/manual.rst
example/README.txt
logrotate/__init__.py
logrotate.egg-info/PKG-INFO
logrotate.egg-info/SOURCES.txt
logrotate.egg-info/dependency_links.txt
logrotate.egg-info/entry_points.txt
logrotate.egg-info/not-zip-safe
logrotate.egg-info/top_level.txt
test/README.txt
test/doc.py