Metadata-Version: 1.0
Name: logrotate
Version: 0.1.0
Summary: A small, simple logrotate implementation for the Python logging module that only rotates files (it doesn't create and delete them) and therefore maintains owner, group and permission information
Home-page: http://jimmyg.org
Author: James Gardner
Author-email: UNKNOWN
License: MIT
Platform: UNKNOWN
Classifier: Development Status :: 3 - Alpha
Classifier: License :: OSI Approved :: GNU Affero General Public License v3
Classifier: Programming Language :: Python
